sbot/__init__.py
sbot/_arduinos.py
sbot/_comp.py
sbot/_leds.py
sbot/_motors.py
sbot/_power.py
sbot/_servos.py
sbot/_utils.py
sbot/_version.py
sbot/_vision.py
sbot/game_specific.py
sbot/marker.py
sbot/py.typed
sbot/robot.py
sbot/historic/__init__.py
sbot/historic/arduino.py
sbot/historic/camera.py
sbot/historic/leds.py
sbot/historic/metadata.py
sbot/historic/motor_board.py
sbot/historic/power_board.py
sbot/historic/robot.py
sbot/historic/servo_board.py
sbot/historic/utils.py
sbot/internal/__init__.py
sbot/internal/board_manager.py
sbot/internal/exceptions.py
sbot/internal/logging.py
sbot/internal/mqtt.py
sbot/internal/overrides.py
sbot/internal/serial_wrapper.py
sbot/internal/start_led.py
sbot/internal/timeout.py
sbot/internal/utils.py
sbot/simulator/__init__.py
sbot/simulator/camera.py
sbot/simulator/led_server.py
sbot/simulator/time_server.py
sbot-2025.1.1.dist-info/licenses/LICENSE
sbot-2025.1.1.dist-info/METADATA
sbot-2025.1.1.dist-info/WHEEL
sbot-2025.1.1.dist-info/top_level.txt
sbot-2025.1.1.dist-info/RECORD
