Metadata-Version: 2.4
Name: sbot
Version: 2025.1.1
Summary: The robot API for the Smallpeice summer school
Author-email: SourceBots <hello@sourcebots.co.uk>
License: MIT License
Project-URL: Repository, https://github.com/sourcebots/sbot
Project-URL: Homepage, https://sourcebots.co.uk
Project-URL: Documentation, https://docs.sourcebots.co.uk
Classifier: Topic :: Software Development :: Libraries :: Python Modules
Classifier: Operating System :: OS Independent
Classifier: Development Status :: 5 - Production/Stable
Classifier: Typing :: Typed
Classifier: Topic :: Education
Requires-Python: >=3.9
License-File: LICENSE
Requires-Dist: pyserial<4,>=3
Requires-Dist: april_vision==3.0.0
Requires-Dist: typing-extensions; python_version < "3.10"
Requires-Dist: python-dotenv==1.0.1
Provides-Extra: dev
Requires-Dist: poethepoet<1,>=0.0.1; extra == "dev"
Requires-Dist: ruff==0.9.8; extra == "dev"
Requires-Dist: mypy==1.10.0; python_version < "3.9" and extra == "dev"
Requires-Dist: mypy<2,>=1.7; python_version >= "3.9" and extra == "dev"
Requires-Dist: build; extra == "dev"
Requires-Dist: types-pyserial; extra == "dev"
Requires-Dist: pytest; extra == "dev"
Requires-Dist: pytest-cov; extra == "dev"
Requires-Dist: paho-mqtt<3,>=2; extra == "dev"
Provides-Extra: vision
Requires-Dist: opencv-python-headless<5,>=4.10; extra == "vision"
Provides-Extra: mqtt
Requires-Dist: paho-mqtt<3,>=2; extra == "mqtt"
Dynamic: license-file
